pygui/__init__.py
pygui/elements.py
pygui/fonts/Roboto-Regular.ttf
pygui/window.py
py_gui_tool-1.6.0.dist-info/LICENSE
py_gui_tool-1.6.0.dist-info/WHEEL
py_gui_tool-1.6.0.dist-info/METADATA
py_gui_tool-1.6.0.dist-info/RECORD
